manimpango/__init__.py
manimpango/_register_font.cp310-win_amd64.pyd
manimpango/_register_font.pxd
manimpango/_register_font.pyx
manimpango/_version.py
manimpango/cairo.pxd
manimpango/cmanimpango.cp310-win_amd64.pyd
manimpango/cmanimpango.pxd
manimpango/cmanimpango.pyx
manimpango/enums.cp310-win_amd64.pyd
manimpango/enums.pyx
manimpango/glib.pxd
manimpango/pango.pxd
manimpango/register_font.py
manimpango/utils.py
manimpango-0.6.1.dist-info/licenses/LICENSE
manimpango-0.6.1.dist-info/licenses/LICENSE.win32
manimpango-0.6.1.dist-info/METADATA
manimpango-0.6.1.dist-info/WHEEL
manimpango-0.6.1.dist-info/top_level.txt
manimpango-0.6.1.dist-info/RECORD
