Metadata-Version: 2.4
Name: ManimPango
Version: 0.6.1
Summary: Bindings for Pango for using with Manim.
Home-page: https://manimpango.manim.community/
Author: Naveen M K
Author-email: naveen@manim.community
Maintainer: The Manim Community Developers
License: MIT
Project-URL: Documentation, https://manimpango.manim.community/
Project-URL: Source, https://github.com/ManimCommunity/manimpango
Project-URL: Release notes, https://github.com/ManimCommunity/ManimPango/releases/
Keywords: cython,pango,cairo,manim
Platform: Linux
Platform: macOS
Platform: Windows
Classifier: Programming Language :: Python :: 3
Classifier: Programming Language :: Python :: 3.8
Classifier: Programming Language :: Python :: 3.9
Classifier: Programming Language :: Python :: 3.10
Classifier: Programming Language :: Python :: 3.11
Classifier: Programming Language :: Python :: 3.12
Classifier: Programming Language :: Python :: 3.13
Classifier: Development Status :: 4 - Beta
Classifier: Programming Language :: Python :: 3 :: Only
Classifier: Programming Language :: Cython
Requires-Python: >=3.8
License-File: LICENSE
License-File: LICENSE.win32
Dynamic: author
Dynamic: author-email
Dynamic: classifier
Dynamic: description
Dynamic: description-content-type
Dynamic: home-page
Dynamic: keywords
Dynamic: license
Dynamic: license-file
Dynamic: maintainer
Dynamic: platform
Dynamic: project-url
Dynamic: requires-python
Dynamic: summary
